warren_video/__init__.py
warren_video/api.py
warren_video/conf.py
warren_video/factories.py
warren_video/indicators.py
warren_video/models.py
warren_video-0.1.0.dist-info/METADATA
warren_video-0.1.0.dist-info/WHEEL
warren_video-0.1.0.dist-info/entry_points.txt
warren_video-0.1.0.dist-info/top_level.txt
warren_video-0.1.0.dist-info/RECORD
