Metadata-Version: 2.1
Name: warren-video
Version: 0.1.0
Summary: The video activity plugin for warren
Author-email: "Open FUN (France Universite Numerique)" <fun.dev@fun-mooc.fr>
Project-URL: Homepage, https://github.com/openfun/warren
Project-URL: Bug Tracker, https://github.com/openfun/warren/issues
Keywords: Analytics,xAPI,LRS,LTI,Video
Classifier: Development Status :: 3 - Alpha
Classifier: Intended Audience :: Developers
Classifier: License :: OSI Approved :: MIT License
Classifier: Natural Language :: English
Classifier: Programming Language :: Python :: 3
Classifier: Programming Language :: Python :: 3.8
Classifier: Programming Language :: Python :: 3.9
Classifier: Programming Language :: Python :: 3.10
Classifier: Programming Language :: Python :: 3.11
Requires-Python: >=3.8
Requires-Dist: warren-api
